[
  {
    "id": 1,
    "title": "Alps",
    "imageUrl": "/images/nature/9E4F17FF-55B9-4643-A2F4-7050369FB8CD copy.PNG",
    "category": "Nature & Landscapes"
  },
  {
    "id": 2,
    "title": "Alps",
    "imageUrl": "/images/nature/C7AC92DE-97BF-4CD3-827F-2865CF38F3EE.PNG",
    "category": "Nature & Landscapes"
  },
  {
    "id": 3,
    "title": "Name Placeholder",
    "imageUrl": "/images/nature/C7AC92DE-97BF-4CD3-827F-2865CF38F3EE copy.PNG",
    "category": "Nature & Landscapes"
  },
  {
    "id": 4,
    "title": "Neuschwanstein",
    "imageUrl": "/images/nature/IMG_9264 copy.JPG",
    "category": "Nature & Landscapes"
  },
  {
    "id": 5,
    "title": "Name Placeholder",
    "imageUrl": "/images/nature/IMG_9264.JPG",
    "category": "Nature & Landscapes"
  },
  {
    "id": 6,
    "title": "Mountains",
    "imageUrl": "/images/nature/mountains.jpg",
    "category": "Nature & Landscapes"
  },
  {
    "id": 7,
    "title": "Name Placeholder",
    "imageUrl": "/images/nature/9E4F17FF-55B9-4643-A2F4-7050369FB8CD.PNG",
    "category": "Nature & Landscapes"
  },
  {
    "id": 8,
    "title": "Name Placeholder",
    "imageUrl": "/images/nature/mountains copy.jpg",
    "category": "Nature & Landscapes"
  },
  {
    "id": 9,
    "title": "Eva",
    "imageUrl": "/images/people/IMG_9007-Улучшено-Ум. шума-4 copy.jpg",
    "category": "Portraits & People"
  },
  {
    "id": 10,
    "title": "Eva",
    "imageUrl": "/images/people/IMG_9007-Улучшено-Ум. шума-4 copy 2.jpg",
    "category": "Portraits & People"
  },
  {
    "id": 11,
    "title": "Eva",
    "imageUrl": "/images/people/IMG_9007-Улучшено-Ум. шума-4 copy 3.jpg",
    "category": "Portraits & People"
  },
  {
    "id": 12,
    "title": "Eva",
    "imageUrl": "/images/people/IMG_9007-Улучшено-Ум. шума-4 copy 4.jpg",
    "category": "Portraits & People"
  },
  {
    "id": 13,
    "title": "Eva",
    "imageUrl": "/images/people/IMG_9007-Улучшено-Ум. шума-4 copy 5.jpg",
    "category": "Portraits & People"
  },
  {
    "id": 14,
    "title": "Eva",
    "imageUrl": "/images/people/IMG_9007-Улучшено-Ум. шума-4 copy 7.jpg",
    "category": "Portraits & People"
  },
  {
    "id": 15,
    "title": "Eva",
    "imageUrl": "/images/people/IMG_9007-Улучшено-Ум. шума-4 copy 6.jpg",
    "category": "Portraits & People"
  },
  {
    "id": 16,
    "title": "Name Placeholder",
    "imageUrl": "/images/people/IMG_9007-Улучшено-Ум. шума-4.jpg",
    "category": "Portraits & People"
  },
  {
    "id": 17,
    "title": "Name Placeholder",
    "imageUrl": "/images/urban/IMG_8267_preview copy.jpeg",
    "category": "Urban & Architecture"
  },
  {
    "id": 18,
    "title": "Name Placeholder",
    "imageUrl": "/images/urban/IMG_8267_preview.jpeg",
    "category": "Urban & Architecture"
  },
  {
    "id": 19,
    "title": "Name Placeholder",
    "imageUrl": "/images/urban/IMG_1074 (1) copy.JPG",
    "category": "Urban & Architecture"
  },
  {
    "id": 20,
    "title": "Name Placeholder",
    "imageUrl": "/images/urban/IMG_8819_preview copy.jpeg",
    "category": "Urban & Architecture"
  },
  {
    "id": 21,
    "title": "Name Placeholder",
    "imageUrl": "/images/urban/IMG_8819_preview.jpeg",
    "category": "Urban & Architecture"
  },
  {
    "id": 22,
    "title": "Name Placeholder",
    "imageUrl": "/images/urban/IMG_1074 (1).JPG",
    "category": "Urban & Architecture"
  }
]